BreastCancerMLPModel/BreastCancerMLPModel.py
BreastCancerMLPModel/__init__.py
BreastCancerMLPModel-0.0.32.dist-info/METADATA
BreastCancerMLPModel-0.0.32.dist-info/WHEEL
BreastCancerMLPModel-0.0.32.dist-info/top_level.txt
BreastCancerMLPModel-0.0.32.dist-info/RECORD
