Metadata-Version: 2.1
Name: BreastCancerMLPModel
Version: 0.0.32
Summary: A package for breast cancer diagnosis using MLP classifier.
Home-page: https://github.com/sergio11/breast_cancer_diagnosis_mlp
Author: Sergio Sánchez Sánchez
Author-email: dreamsoftware92@gmail.com
Classifier: Development Status :: 4 - Beta
Classifier: Intended Audience :: Developers
Classifier: License :: OSI Approved :: MIT License
Classifier: Programming Language :: Python :: 3
Classifier: Programming Language :: Python :: 3.7
Classifier: Programming Language :: Python :: 3.8
Classifier: Programming Language :: Python :: 3.9
Classifier: Programming Language :: Python :: 3.10
Requires-Python: >=3.7, <4
Requires-Dist: scikit-learn ==1.4.2
Requires-Dist: numpy ==1.25.2
